pymagsac/pymagsac.cpython-310-x86_64-linux-gnu.so
pymagsac/__init__.py
pymagsac_testing.libs/libopencv_flann-80c081ea.so.3.4.5
pymagsac_testing.libs/libopencv_core-4ac423c3.so.3.4.5
pymagsac_testing.libs/libgflags-f1543f81.so.2.1
pymagsac_testing.libs/libopencv_features2d-0eb98270.so.3.4.5
pymagsac_testing.libs/libopencv_imgproc-458179af.so.3.4.5
pymagsac_testing.libs/libopencv_calib3d-b2e6635f.so.3.4.5
pymagsac_testing-0.3.0.dist-info/LICENSE
pymagsac_testing-0.3.0.dist-info/top_level.txt
pymagsac_testing-0.3.0.dist-info/RECORD
pymagsac_testing-0.3.0.dist-info/METADATA
pymagsac_testing-0.3.0.dist-info/WHEEL
